encrypted_files/__init__.py
encrypted_files/apps.py
encrypted_files/base.py
encrypted_files/uploadhandler.py
django_encrypted_files-0.0.10.dist-info/LICENSE
django_encrypted_files-0.0.10.dist-info/METADATA
django_encrypted_files-0.0.10.dist-info/WHEEL
django_encrypted_files-0.0.10.dist-info/top_level.txt
django_encrypted_files-0.0.10.dist-info/RECORD
