Metadata-Version: 2.1
Name: django-encrypted-files
Version: 0.0.10
Summary: Encrypt files uploaded to a Django application.
Home-page: https://github.com/eblocha/django-encrypted-files
Author: Elliott Blocha
License: MIT
Keywords: cryptography,big,large,encryption
Classifier: Development Status :: 3 - Alpha
Classifier: Topic :: Utilities
Classifier: License :: OSI Approved :: MIT License
Classifier: Programming Language :: Python :: 3
Classifier: Programming Language :: Python :: 3.6
Classifier: Programming Language :: Python :: 3.7
Classifier: Programming Language :: Python :: 3.8
Classifier: Programming Language :: Python :: 3.9
Classifier: Programming Language :: Python :: 3 :: Only
Requires-Python: >=3.6, <4
License-File: LICENSE
